optical_trace/__init__.py
optical_trace/optical_trace.py
optical_tracer-0.2.0.dist-info/METADATA
optical_tracer-0.2.0.dist-info/WHEEL
optical_tracer-0.2.0.dist-info/top_level.txt
optical_tracer-0.2.0.dist-info/RECORD
